AsposePDFPython/3rdParty.pdf
AsposePDFPython/AsposePDFPython.cpython-310-darwin.so
AsposePDFPython/AsposePDFPython.cpython-311-darwin.so
AsposePDFPython/AsposePDFPython.cpython-312-darwin.so
AsposePDFPython/AsposePDFPython.cpython-313-darwin.so
AsposePDFPython/AsposePDFPython.cpython-38-darwin.so
AsposePDFPython/AsposePDFPython.cpython-39-darwin.so
AsposePDFPython/LICENSE
AsposePDFPython/__init__.py
AsposePDFPython/libAspose.PDF.Cpp_appleclang_x86_64.dylib
AsposePDFPythonWrappers/__init__.py
AsposePDFPythonWrappers/artifact.py
AsposePDFPythonWrappers/artifact_collection.py
AsposePDFPythonWrappers/base_paragraph.py
AsposePDFPythonWrappers/color.py
AsposePDFPythonWrappers/document.py
AsposePDFPythonWrappers/file_hyperlink.py
AsposePDFPythonWrappers/hyperlink.py
AsposePDFPythonWrappers/i_warning_callback.py
AsposePDFPythonWrappers/image.py
AsposePDFPythonWrappers/image_stamp.py
AsposePDFPythonWrappers/layer.py
AsposePDFPythonWrappers/license.py
AsposePDFPythonWrappers/local_hyperlink.py
AsposePDFPythonWrappers/margin_info.py
AsposePDFPythonWrappers/note.py
AsposePDFPythonWrappers/page.py
AsposePDFPythonWrappers/page_collection.py
AsposePDFPythonWrappers/page_number_stamp.py
AsposePDFPythonWrappers/paragraphs.py
AsposePDFPythonWrappers/point.py
AsposePDFPythonWrappers/rectangle.py
AsposePDFPythonWrappers/stamp.py
AsposePDFPythonWrappers/text_stamp.py
AsposePDFPythonWrappers/warning_info.py
AsposePDFPythonWrappers/web_hyperlink.py
AsposePDFPythonWrappers/devices/__init__.py
AsposePDFPythonWrappers/devices/device.py
AsposePDFPythonWrappers/devices/image_device.py
AsposePDFPythonWrappers/devices/jpeg_device.py
AsposePDFPythonWrappers/devices/page_device.py
AsposePDFPythonWrappers/devices/png_device.py
AsposePDFPythonWrappers/devices/resolution.py
AsposePDFPythonWrappers/facades/__init__.py
AsposePDFPythonWrappers/facades/facade.py
AsposePDFPythonWrappers/facades/form_editor.py
AsposePDFPythonWrappers/facades/form_field_facade.py
aspose_pdf_cpp_for_python-25.9.4.dist-info/METADATA
aspose_pdf_cpp_for_python-25.9.4.dist-info/WHEEL
aspose_pdf_cpp_for_python-25.9.4.dist-info/top_level.txt
aspose_pdf_cpp_for_python-25.9.4.dist-info/RECORD
