Metadata-Version: 2.4
Name: aspose-pdf-cpp-for-python
Version: 25.9.4
Summary: Aspose PDF Python via C++
Home-page: https://products.aspose.com/pdf/python-cpp/
Author: Aspose
License: Other/Proprietary License
Project-URL: Blog, https://blog.aspose.com/categories/aspose.pdf-product-family/
Project-URL: Demos, https://products.aspose.app/pdf/family/
Project-URL: Docs, https://docs.aspose.com/pdf/python-cpp/
Project-URL: Free Support, https://forum.aspose.com/c/pdf/10
Project-URL: API Reference, https://reference.aspose.com/pdf/python-cpp/
Project-URL: Temporary License, https://purchase.aspose.com/temporary-license
Keywords: Aspose.PDF,PDF
Platform: darwin
Classifier: Development Status :: 5 - Production/Stable
Classifier: Intended Audience :: Developers
Classifier: Intended Audience :: Education
Classifier: License :: Other/Proprietary License
Classifier: Operating System :: Microsoft :: Windows
Classifier: Operating System :: POSIX :: Linux
Classifier: Operating System :: Unix
Classifier: Programming Language :: Python :: 3 :: Only
Classifier: Programming Language :: Python :: 3.8
Classifier: Programming Language :: Python :: 3.9
Classifier: Programming Language :: Python :: 3.10
Classifier: Programming Language :: Python :: 3.11
Classifier: Programming Language :: Python :: 3.12
Classifier: Programming Language :: Python :: 3.13
Classifier: Topic :: Software Development
Classifier: Topic :: Software Development :: Libraries
Classifier: Topic :: Office/Business
Classifier: Topic :: Office/Business :: Office Suites
Requires-Python: >=3.8,<3.14
Dynamic: author
Dynamic: classifier
Dynamic: description
Dynamic: description-content-type
Dynamic: home-page
Dynamic: keywords
Dynamic: license
Dynamic: platform
Dynamic: project-url
Dynamic: requires-python
Dynamic: summary
